{
  "All": {
    "OnScreen": {
      "A": "mouseright",
      "B": "mouseleft",
      "Pointer": "lightgunmouse",
      "Home": "home",
      "Down": "down",
      "Up": "up",
      "Right": "right",
      "Left": "left",
      "Plus": "vk_1",
      "Minus": "vk_5",
      "One": "mousexbutton1",
      "Two": "mousexbutton2",
      "Shake": "mouseright",
      "Nunchuk.C": "rshift",
      "Nunchuk.Z": "lshift",
      "Nunchuk.StickUp": "vk_w",
      "Nunchuk.StickDown": "vk_s",
      "Nunchuk.StickLeft": "vk_a",
      "Nunchuk.StickRight": "vk_d",
      "Classic.Left": "Deshabilitada",
      "Classic.Right": "Deshabilitada",
      "Classic.Up": "Deshabilitada",
      "Classic.Down": "Deshabilitada",
      "Classic.StickLLeft": "Deshabilitada",
      "Classic.StickLRight": "Deshabilitada",
      "Classic.StickLUp": "Deshabilitada",
      "Classic.StickLDown": "Deshabilitada",
      "Classic.StickRLeft": "Deshabilitada",
      "Classic.StickRRight": "Deshabilitada",
      "Classic.StickRUp": "Deshabilitada",
      "Classic.StickRDown": "Deshabilitada",
      "Classic.Minus": "Deshabilitada",
      "Classic.Plus": "Deshabilitada",
      "Classic.Home": "Deshabilitada",
      "Classic.Y": "Deshabilitada",
      "Classic.X": "Deshabilitada",
      "Classic.A": "Deshabilitada",
      "Classic.B": "Deshabilitada",
      "Classic.TriggerL": "Deshabilitada",
      "Classic.TriggerR": "Deshabilitada",
      "Classic.ZL": "Deshabilitada",
      "Classic.ZR": "Deshabilitada"
    },
    "OffScreen": {
      "B": "mouseright"
    }
  },
  "Title": "Mouse Lightgun"
}